badger/__init__.py
badger/__main__.py
badger/_version.py
badger/archive.py
badger/core.py
badger/core_subprocess.py
badger/db.py
badger/environment.py
badger/errors.py
badger/extension.py
badger/factory.py
badger/interface.py
badger/log.py
badger/logbook.py
badger/routine.py
badger/settings.py
badger/stats.py
badger/utils.py
badger/actions/__init__.py
badger/actions/config.py
badger/actions/doctor.py
badger/actions/env.py
badger/actions/generator.py
badger/actions/install.py
badger/actions/intf.py
badger/actions/routine.py
badger/actions/run.py
badger/actions/uninstall.py
badger/built_in_plugins/environments/sphere_2d/README.md
badger/built_in_plugins/environments/sphere_2d/__init__.py
badger/built_in_plugins/environments/sphere_2d/configs.yaml
badger/built_in_plugins/interfaces/default/README.md
badger/built_in_plugins/interfaces/default/__init__.py
badger/built_in_plugins/interfaces/default/configs.yaml
badger/gui/__init__.py
badger/gui/default/__init__.py
badger/gui/default/utils.py
badger/gui/default/components/__init__.py
badger/gui/default/components/analysis_extensions.py
badger/gui/default/components/collapsible_box.py
badger/gui/default/components/constraint_item.py
badger/gui/default/components/create_process.py
badger/gui/default/components/data_table.py
badger/gui/default/components/eliding_label.py
badger/gui/default/components/env_cbox.py
badger/gui/default/components/extensions_palette.py
badger/gui/default/components/filter_cbox.py
badger/gui/default/components/generator_cbox.py
badger/gui/default/components/history_navigator.py
badger/gui/default/components/labeled_lineedit.py
badger/gui/default/components/obj_table.py
badger/gui/default/components/process_manager.py
badger/gui/default/components/reorderable_table.py
badger/gui/default/components/robust_spinbox.py
badger/gui/default/components/routine_editor.py
badger/gui/default/components/routine_item.py
badger/gui/default/components/routine_page.py
badger/gui/default/components/routine_runner.py
badger_opt-1.1.3.dist-info/LICENSE
badger_opt-1.1.3.dist-info/METADATA
badger_opt-1.1.3.dist-info/WHEEL
badger_opt-1.1.3.dist-info/entry_points.txt
badger_opt-1.1.3.dist-info/top_level.txt
badger_opt-1.1.3.dist-info/RECORD
