Metadata-Version: 2.1
Name: badger-opt
Version: 1.1.3
Summary: Core of the Badger optimizer
Home-page: https://github.com/SLAC-ML/Badger
Author: Zhe Zhang
Author-email: zhezhang@slac.stanford.edu
License: GPL
Requires-Python: >=3.9
License-File: LICENSE
Requires-Dist: pandas
Requires-Dist: pyyaml
Requires-Dist: coolname
Requires-Dist: pyqt5
Requires-Dist: pyqtgraph
Requires-Dist: qdarkstyle
Requires-Dist: pillow
Requires-Dist: requests
Requires-Dist: tqdm
Requires-Dist: xopt
Provides-Extra: dev
Requires-Dist: pytest; extra == "dev"
Requires-Dist: pytest-qt; extra == "dev"
Requires-Dist: pytest-mock; extra == "dev"
